pyextension/__init__.py
pyextension/mathematics.py
pyextension/password.py
pyextension/test.py
pyextension/unicode.py
pyextension/word_bank/__init__.py
tkextension/__init__.py
tkextension/system.py
tkextension/test.py
tkextension/turtledrawer.py
tkextension/tix/__init__.py
tkextension/tix/blackboard.py
tkextension/tix/card.py
tkextension/tix/filedialog.py
tkextension/tix/listmenu.py
tkextension/tix/timer.py
Python_Extension-2.0.0.dist-info/LICENSE.txt
Python_Extension-2.0.0.dist-info/METADATA
Python_Extension-2.0.0.dist-info/WHEEL
Python_Extension-2.0.0.dist-info/top_level.txt
Python_Extension-2.0.0.dist-info/RECORD
