Metadata-Version: 2.1
Name: Python-Extension
Version: 2.0.0
Summary: Python extension functions
Home-page: UNKNOWN
Author: Yile Wang
Author-email: bluewindde@163.com
License: GPL
Platform: UNKNOWN
Requires-Python: >=2.7
License-File: LICENSE.txt
